<GFXVectorList>
<id>
17224</id>
<order>
17224</order>
<GFXVector>
<startVertex>
<x>
0.0</x>
<y>
4.0</y>
<z>
0.0</z>
<w>
1.0</w>
<use_x>
true</use_x>
<use_y>
true</use_y>
<use_z>
true</use_z>
<use_w>
true</use_w>
<id>
4018666</id>
</startVertex>
<endVertex>
<x>
2.0</x>
<y>
3.0</y>
<z>
0.0</z>
<w>
1.0</w>
<use_x>
true</use_x>
<use_y>
true</use_y>
<use_z>
true</use_z>
<use_w>
true</use_w>
<id>
4018667</id>
</endVertex>
<pattern>
255</pattern>
<r>
255</r>
<g>
255</g>
<b>
255</b>
<a>
128</a>
<id>
286689</id>
<order>
0</order>
<start_neighbour_id>
-1</start_neighbour_id>
<end_neighbour_id>
-1</end_neighbour_id>
<start_is_relative>
false</start_is_relative>
<end_is_relative>
false</end_is_relative>
<is_3d>
false</is_3d>
<intensity>
63</intensity>
</GFXVector>
<GFXVector>
<startVertex>
<x>
2.0</x>
<y>
3.0</y>
<z>
0.0</z>
<w>
1.0</w>
<use_x>
true</use_x>
<use_y>
true</use_y>
<use_z>
true</use_z>
<use_w>
true</use_w>
<id>
4018668</id>
</startVertex>
<endVertex>
<x>
2.0</x>
<y>
1.0</y>
<z>
0.0</z>
<w>
1.0</w>
<use_x>
true</use_x>
<use_y>
true</use_y>
<use_z>
true</use_z>
<use_w>
true</use_w>
<id>
4018669</id>
</endVertex>
<pattern>
255</pattern>
<r>
255</r>
<g>
255</g>
<b>
255</b>
<a>
128</a>
<id>
286690</id>
<order>
1</order>
<start_neighbour_id>
-1</start_neighbour_id>
<end_neighbour_id>
286691</end_neighbour_id>
<start_is_relative>
false</start_is_relative>
<end_is_relative>
false</end_is_relative>
<is_3d>
false</is_3d>
<intensity>
63</intensity>
</GFXVector>
<GFXVector>
<startVertex>
<x>
2.0</x>
<y>
1.0</y>
<z>
0.0</z>
<w>
1.0</w>
<use_x>
true</use_x>
<use_y>
true</use_y>
<use_z>
true</use_z>
<use_w>
true</use_w>
<id>
4018669</id>
</startVertex>
<endVertex>
<x>
3.0</x>
<y>
0.0</y>
<z>
0.0</z>
<w>
1.0</w>
<use_x>
true</use_x>
<use_y>
true</use_y>
<use_z>
true</use_z>
<use_w>
true</use_w>
<id>
4018671</id>
</endVertex>
<pattern>
255</pattern>
<r>
255</r>
<g>
255</g>
<b>
255</b>
<a>
128</a>
<id>
286691</id>
<order>
2</order>
<start_neighbour_id>
286690</start_neighbour_id>
<end_neighbour_id>
-1</end_neighbour_id>
<start_is_relative>
false</start_is_relative>
<end_is_relative>
false</end_is_relative>
<is_3d>
false</is_3d>
<intensity>
63</intensity>
</GFXVector>
<GFXVector>
<startVertex>
<x>
3.0</x>
<y>
0.0</y>
<z>
0.0</z>
<w>
1.0</w>
<use_x>
true</use_x>
<use_y>
true</use_y>
<use_z>
true</use_z>
<use_w>
true</use_w>
<id>
4018672</id>
</startVertex>
<endVertex>
<x>
0.0</x>
<y>
-1.0</y>
<z>
0.0</z>
<w>
1.0</w>
<use_x>
true</use_x>
<use_y>
true</use_y>
<use_z>
true</use_z>
<use_w>
true</use_w>
<id>
4018673</id>
</endVertex>
<pattern>
255</pattern>
<r>
255</r>
<g>
255</g>
<b>
255</b>
<a>
128</a>
<id>
286692</id>
<order>
3</order>
<start_neighbour_id>
-1</start_neighbour_id>
<end_neighbour_id>
286693</end_neighbour_id>
<start_is_relative>
false</start_is_relative>
<end_is_relative>
false</end_is_relative>
<is_3d>
false</is_3d>
<intensity>
63</intensity>
</GFXVector>
<GFXVector>
<startVertex>
<x>
0.0</x>
<y>
-1.0</y>
<z>
0.0</z>
<w>
1.0</w>
<use_x>
true</use_x>
<use_y>
true</use_y>
<use_z>
true</use_z>
<use_w>
true</use_w>
<id>
4018673</id>
</startVertex>
<endVertex>
<x>
-3.0</x>
<y>
0.0</y>
<z>
0.0</z>
<w>
1.0</w>
<use_x>
true</use_x>
<use_y>
true</use_y>
<use_z>
true</use_z>
<use_w>
true</use_w>
<id>
4018675</id>
</endVertex>
<pattern>
255</pattern>
<r>
255</r>
<g>
255</g>
<b>
255</b>
<a>
128</a>
<id>
286693</id>
<order>
4</order>
<start_neighbour_id>
286692</start_neighbour_id>
<end_neighbour_id>
-1</end_neighbour_id>
<start_is_relative>
false</start_is_relative>
<end_is_relative>
false</end_is_relative>
<is_3d>
false</is_3d>
<intensity>
63</intensity>
</GFXVector>
<GFXVector>
<startVertex>
<x>
-3.0</x>
<y>
0.0</y>
<z>
0.0</z>
<w>
1.0</w>
<use_x>
true</use_x>
<use_y>
true</use_y>
<use_z>
true</use_z>
<use_w>
true</use_w>
<id>
4018676</id>
</startVertex>
<endVertex>
<x>
-2.0</x>
<y>
1.0</y>
<z>
0.0</z>
<w>
1.0</w>
<use_x>
true</use_x>
<use_y>
true</use_y>
<use_z>
true</use_z>
<use_w>
true</use_w>
<id>
4018677</id>
</endVertex>
<pattern>
255</pattern>
<r>
255</r>
<g>
255</g>
<b>
255</b>
<a>
128</a>
<id>
286694</id>
<order>
5</order>
<start_neighbour_id>
-1</start_neighbour_id>
<end_neighbour_id>
286695</end_neighbour_id>
<start_is_relative>
false</start_is_relative>
<end_is_relative>
false</end_is_relative>
<is_3d>
false</is_3d>
<intensity>
63</intensity>
</GFXVector>
<GFXVector>
<startVertex>
<x>
-2.0</x>
<y>
1.0</y>
<z>
0.0</z>
<w>
1.0</w>
<use_x>
true</use_x>
<use_y>
true</use_y>
<use_z>
true</use_z>
<use_w>
true</use_w>
<id>
4018677</id>
</startVertex>
<endVertex>
<x>
-2.0</x>
<y>
3.0</y>
<z>
0.0</z>
<w>
1.0</w>
<use_x>
true</use_x>
<use_y>
true</use_y>
<use_z>
true</use_z>
<use_w>
true</use_w>
<id>
4018679</id>
</endVertex>
<pattern>
255</pattern>
<r>
255</r>
<g>
255</g>
<b>
255</b>
<a>
128</a>
<id>
286695</id>
<order>
6</order>
<start_neighbour_id>
286694</start_neighbour_id>
<end_neighbour_id>
-1</end_neighbour_id>
<start_is_relative>
false</start_is_relative>
<end_is_relative>
false</end_is_relative>
<is_3d>
false</is_3d>
<intensity>
63</intensity>
</GFXVector>
<GFXVector>
<startVertex>
<x>
-2.0</x>
<y>
3.0</y>
<z>
0.0</z>
<w>
1.0</w>
<use_x>
true</use_x>
<use_y>
true</use_y>
<use_z>
true</use_z>
<use_w>
true</use_w>
<id>
4018680</id>
</startVertex>
<endVertex>
<x>
0.0</x>
<y>
4.0</y>
<z>
0.0</z>
<w>
1.0</w>
<use_x>
true</use_x>
<use_y>
true</use_y>
<use_z>
true</use_z>
<use_w>
true</use_w>
<id>
4018681</id>
</endVertex>
<pattern>
255</pattern>
<r>
255</r>
<g>
255</g>
<b>
255</b>
<a>
128</a>
<id>
286696</id>
<order>
7</order>
<start_neighbour_id>
-1</start_neighbour_id>
<end_neighbour_id>
-1</end_neighbour_id>
<start_is_relative>
false</start_is_relative>
<end_is_relative>
false</end_is_relative>
<is_3d>
false</is_3d>
<intensity>
63</intensity>
</GFXVector>
<GFXVector>
<startVertex>
<x>
3.0</x>
<y>
0.0</y>
<z>
0.0</z>
<w>
1.0</w>
<use_x>
true</use_x>
<use_y>
true</use_y>
<use_z>
true</use_z>
<use_w>
true</use_w>
<id>
4018682</id>
</startVertex>
<endVertex>
<x>
7.0</x>
<y>
-1.0</y>
<z>
0.0</z>
<w>
1.0</w>
<use_x>
true</use_x>
<use_y>
true</use_y>
<use_z>
true</use_z>
<use_w>
true</use_w>
<id>
4018683</id>
</endVertex>
<pattern>
255</pattern>
<r>
255</r>
<g>
255</g>
<b>
255</b>
<a>
128</a>
<id>
286697</id>
<order>
8</order>
<start_neighbour_id>
-1</start_neighbour_id>
<end_neighbour_id>
-1</end_neighbour_id>
<start_is_relative>
false</start_is_relative>
<end_is_relative>
false</end_is_relative>
<is_3d>
false</is_3d>
<intensity>
63</intensity>
</GFXVector>
<GFXVector>
<startVertex>
<x>
7.0</x>
<y>
-1.0</y>
<z>
0.0</z>
<w>
1.0</w>
<use_x>
true</use_x>
<use_y>
true</use_y>
<use_z>
true</use_z>
<use_w>
true</use_w>
<id>
4018684</id>
</startVertex>
<endVertex>
<x>
7.0</x>
<y>
-6.0</y>
<z>
0.0</z>
<w>
1.0</w>
<use_x>
true</use_x>
<use_y>
true</use_y>
<use_z>
true</use_z>
<use_w>
true</use_w>
<id>
4018685</id>
</endVertex>
<pattern>
255</pattern>
<r>
255</r>
<g>
255</g>
<b>
255</b>
<a>
128</a>
<id>
286698</id>
<order>
9</order>
<start_neighbour_id>
-1</start_neighbour_id>
<end_neighbour_id>
-1</end_neighbour_id>
<start_is_relative>
false</start_is_relative>
<end_is_relative>
false</end_is_relative>
<is_3d>
false</is_3d>
<intensity>
63</intensity>
</GFXVector>
<GFXVector>
<startVertex>
<x>
7.0</x>
<y>
-6.0</y>
<z>
0.0</z>
<w>
1.0</w>
<use_x>
true</use_x>
<use_y>
true</use_y>
<use_z>
true</use_z>
<use_w>
true</use_w>
<id>
4018686</id>
</startVertex>
<endVertex>
<x>
4.0</x>
<y>
-7.0</y>
<z>
0.0</z>
<w>
1.0</w>
<use_x>
true</use_x>
<use_y>
true</use_y>
<use_z>
true</use_z>
<use_w>
true</use_w>
<id>
4018687</id>
</endVertex>
<pattern>
255</pattern>
<r>
255</r>
<g>
255</g>
<b>
255</b>
<a>
128</a>
<id>
286699</id>
<order>
10</order>
<start_neighbour_id>
-1</start_neighbour_id>
<end_neighbour_id>
-1</end_neighbour_id>
<start_is_relative>
false</start_is_relative>
<end_is_relative>
false</end_is_relative>
<is_3d>
false</is_3d>
<intensity>
63</intensity>
</GFXVector>
<GFXVector>
<startVertex>
<x>
4.0</x>
<y>
-7.0</y>
<z>
0.0</z>
<w>
1.0</w>
<use_x>
true</use_x>
<use_y>
true</use_y>
<use_z>
true</use_z>
<use_w>
true</use_w>
<id>
4018688</id>
</startVertex>
<endVertex>
<x>
0.0</x>
<y>
-1.0</y>
<z>
0.0</z>
<w>
1.0</w>
<use_x>
true</use_x>
<use_y>
true</use_y>
<use_z>
true</use_z>
<use_w>
true</use_w>
<id>
4018689</id>
</endVertex>
<pattern>
255</pattern>
<r>
255</r>
<g>
255</g>
<b>
255</b>
<a>
128</a>
<id>
286700</id>
<order>
11</order>
<start_neighbour_id>
-1</start_neighbour_id>
<end_neighbour_id>
-1</end_neighbour_id>
<start_is_relative>
false</start_is_relative>
<end_is_relative>
false</end_is_relative>
<is_3d>
false</is_3d>
<intensity>
63</intensity>
</GFXVector>
<GFXVector>
<startVertex>
<x>
0.0</x>
<y>
-1.0</y>
<z>
0.0</z>
<w>
1.0</w>
<use_x>
true</use_x>
<use_y>
true</use_y>
<use_z>
true</use_z>
<use_w>
true</use_w>
<id>
4018690</id>
</startVertex>
<endVertex>
<x>
-4.0</x>
<y>
-7.0</y>
<z>
0.0</z>
<w>
1.0</w>
<use_x>
true</use_x>
<use_y>
true</use_y>
<use_z>
true</use_z>
<use_w>
true</use_w>
<id>
4018691</id>
</endVertex>
<pattern>
255</pattern>
<r>
255</r>
<g>
255</g>
<b>
255</b>
<a>
128</a>
<id>
286701</id>
<order>
12</order>
<start_neighbour_id>
-1</start_neighbour_id>
<end_neighbour_id>
-1</end_neighbour_id>
<start_is_relative>
false</start_is_relative>
<end_is_relative>
false</end_is_relative>
<is_3d>
false</is_3d>
<intensity>
63</intensity>
</GFXVector>
<GFXVector>
<startVertex>
<x>
-4.0</x>
<y>
-7.0</y>
<z>
0.0</z>
<w>
1.0</w>
<use_x>
true</use_x>
<use_y>
true</use_y>
<use_z>
true</use_z>
<use_w>
true</use_w>
<id>
4018692</id>
</startVertex>
<endVertex>
<x>
-7.0</x>
<y>
-6.0</y>
<z>
0.0</z>
<w>
1.0</w>
<use_x>
true</use_x>
<use_y>
true</use_y>
<use_z>
true</use_z>
<use_w>
true</use_w>
<id>
4018693</id>
</endVertex>
<pattern>
255</pattern>
<r>
255</r>
<g>
255</g>
<b>
255</b>
<a>
128</a>
<id>
286702</id>
<order>
13</order>
<start_neighbour_id>
-1</start_neighbour_id>
<end_neighbour_id>
-1</end_neighbour_id>
<start_is_relative>
false</start_is_relative>
<end_is_relative>
false</end_is_relative>
<is_3d>
false</is_3d>
<intensity>
63</intensity>
</GFXVector>
<GFXVector>
<startVertex>
<x>
-7.0</x>
<y>
-6.0</y>
<z>
0.0</z>
<w>
1.0</w>
<use_x>
true</use_x>
<use_y>
true</use_y>
<use_z>
true</use_z>
<use_w>
true</use_w>
<id>
4018694</id>
</startVertex>
<endVertex>
<x>
-7.0</x>
<y>
-1.0</y>
<z>
0.0</z>
<w>
1.0</w>
<use_x>
true</use_x>
<use_y>
true</use_y>
<use_z>
true</use_z>
<use_w>
true</use_w>
<id>
4018695</id>
</endVertex>
<pattern>
255</pattern>
<r>
255</r>
<g>
255</g>
<b>
255</b>
<a>
128</a>
<id>
286703</id>
<order>
14</order>
<start_neighbour_id>
-1</start_neighbour_id>
<end_neighbour_id>
-1</end_neighbour_id>
<start_is_relative>
false</start_is_relative>
<end_is_relative>
false</end_is_relative>
<is_3d>
false</is_3d>
<intensity>
63</intensity>
</GFXVector>
<GFXVector>
<startVertex>
<x>
-7.0</x>
<y>
-1.0</y>
<z>
0.0</z>
<w>
1.0</w>
<use_x>
true</use_x>
<use_y>
true</use_y>
<use_z>
true</use_z>
<use_w>
true</use_w>
<id>
4018696</id>
</startVertex>
<endVertex>
<x>
-3.0</x>
<y>
0.0</y>
<z>
0.0</z>
<w>
1.0</w>
<use_x>
true</use_x>
<use_y>
true</use_y>
<use_z>
true</use_z>
<use_w>
true</use_w>
<id>
4018697</id>
</endVertex>
<pattern>
255</pattern>
<r>
255</r>
<g>
255</g>
<b>
255</b>
<a>
128</a>
<id>
286704</id>
<order>
15</order>
<start_neighbour_id>
-1</start_neighbour_id>
<end_neighbour_id>
-1</end_neighbour_id>
<start_is_relative>
false</start_is_relative>
<end_is_relative>
false</end_is_relative>
<is_3d>
false</is_3d>
<intensity>
63</intensity>
</GFXVector>
<GFXVector>
<startVertex>
<x>
-2.0</x>
<y>
3.0</y>
<z>
0.0</z>
<w>
1.0</w>
<use_x>
true</use_x>
<use_y>
true</use_y>
<use_z>
true</use_z>
<use_w>
true</use_w>
<id>
4018698</id>
</startVertex>
<endVertex>
<x>
-3.0</x>
<y>
4.0</y>
<z>
0.0</z>
<w>
1.0</w>
<use_x>
true</use_x>
<use_y>
true</use_y>
<use_z>
true</use_z>
<use_w>
true</use_w>
<id>
4018699</id>
</endVertex>
<pattern>
255</pattern>
<r>
255</r>
<g>
255</g>
<b>
255</b>
<a>
128</a>
<id>
286705</id>
<order>
16</order>
<start_neighbour_id>
-1</start_neighbour_id>
<end_neighbour_id>
-1</end_neighbour_id>
<start_is_relative>
false</start_is_relative>
<end_is_relative>
false</end_is_relative>
<is_3d>
false</is_3d>
<intensity>
63</intensity>
</GFXVector>
<GFXVector>
<startVertex>
<x>
-3.0</x>
<y>
4.0</y>
<z>
0.0</z>
<w>
1.0</w>
<use_x>
true</use_x>
<use_y>
true</use_y>
<use_z>
true</use_z>
<use_w>
true</use_w>
<id>
4018700</id>
</startVertex>
<endVertex>
<x>
-3.0</x>
<y>
7.0</y>
<z>
0.0</z>
<w>
1.0</w>
<use_x>
true</use_x>
<use_y>
true</use_y>
<use_z>
true</use_z>
<use_w>
true</use_w>
<id>
4018701</id>
</endVertex>
<pattern>
255</pattern>
<r>
255</r>
<g>
255</g>
<b>
255</b>
<a>
128</a>
<id>
286706</id>
<order>
17</order>
<start_neighbour_id>
-1</start_neighbour_id>
<end_neighbour_id>
-1</end_neighbour_id>
<start_is_relative>
false</start_is_relative>
<end_is_relative>
false</end_is_relative>
<is_3d>
false</is_3d>
<intensity>
63</intensity>
</GFXVector>
<GFXVector>
<startVertex>
<x>
2.0</x>
<y>
3.0</y>
<z>
0.0</z>
<w>
1.0</w>
<use_x>
true</use_x>
<use_y>
true</use_y>
<use_z>
true</use_z>
<use_w>
true</use_w>
<id>
4018702</id>
</startVertex>
<endVertex>
<x>
3.0</x>
<y>
4.0</y>
<z>
0.0</z>
<w>
1.0</w>
<use_x>
true</use_x>
<use_y>
true</use_y>
<use_z>
true</use_z>
<use_w>
true</use_w>
<id>
4018703</id>
</endVertex>
<pattern>
255</pattern>
<r>
255</r>
<g>
255</g>
<b>
255</b>
<a>
128</a>
<id>
286707</id>
<order>
18</order>
<start_neighbour_id>
-1</start_neighbour_id>
<end_neighbour_id>
-1</end_neighbour_id>
<start_is_relative>
false</start_is_relative>
<end_is_relative>
false</end_is_relative>
<is_3d>
false</is_3d>
<intensity>
63</intensity>
</GFXVector>
<GFXVector>
<startVertex>
<x>
3.0</x>
<y>
4.0</y>
<z>
0.0</z>
<w>
1.0</w>
<use_x>
true</use_x>
<use_y>
true</use_y>
<use_z>
true</use_z>
<use_w>
true</use_w>
<id>
4018704</id>
</startVertex>
<endVertex>
<x>
3.0</x>
<y>
7.0</y>
<z>
0.0</z>
<w>
1.0</w>
<use_x>
true</use_x>
<use_y>
true</use_y>
<use_z>
true</use_z>
<use_w>
true</use_w>
<id>
4018705</id>
</endVertex>
<pattern>
255</pattern>
<r>
255</r>
<g>
255</g>
<b>
255</b>
<a>
128</a>
<id>
286708</id>
<order>
19</order>
<start_neighbour_id>
-1</start_neighbour_id>
<end_neighbour_id>
-1</end_neighbour_id>
<start_is_relative>
false</start_is_relative>
<end_is_relative>
false</end_is_relative>
<is_3d>
false</is_3d>
<intensity>
63</intensity>
</GFXVector>
<GFXVector>
<startVertex>
<x>
2.0</x>
<y>
1.0</y>
<z>
0.0</z>
<w>
1.0</w>
<use_x>
true</use_x>
<use_y>
true</use_y>
<use_z>
true</use_z>
<use_w>
true</use_w>
<id>
4018706</id>
</startVertex>
<endVertex>
<x>
4.0</x>
<y>
3.0</y>
<z>
0.0</z>
<w>
1.0</w>
<use_x>
true</use_x>
<use_y>
true</use_y>
<use_z>
true</use_z>
<use_w>
true</use_w>
<id>
4018707</id>
</endVertex>
<pattern>
255</pattern>
<r>
255</r>
<g>
255</g>
<b>
255</b>
<a>
128</a>
<id>
286709</id>
<order>
20</order>
<start_neighbour_id>
-1</start_neighbour_id>
<end_neighbour_id>
-1</end_neighbour_id>
<start_is_relative>
false</start_is_relative>
<end_is_relative>
false</end_is_relative>
<is_3d>
false</is_3d>
<intensity>
63</intensity>
</GFXVector>
<GFXVector>
<startVertex>
<x>
4.0</x>
<y>
3.0</y>
<z>
0.0</z>
<w>
1.0</w>
<use_x>
true</use_x>
<use_y>
true</use_y>
<use_z>
true</use_z>
<use_w>
true</use_w>
<id>
4018708</id>
</startVertex>
<endVertex>
<x>
6.0</x>
<y>
2.0</y>
<z>
0.0</z>
<w>
1.0</w>
<use_x>
true</use_x>
<use_y>
true</use_y>
<use_z>
true</use_z>
<use_w>
true</use_w>
<id>
4018709</id>
</endVertex>
<pattern>
255</pattern>
<r>
255</r>
<g>
255</g>
<b>
255</b>
<a>
128</a>
<id>
286710</id>
<order>
21</order>
<start_neighbour_id>
-1</start_neighbour_id>
<end_neighbour_id>
-1</end_neighbour_id>
<start_is_relative>
false</start_is_relative>
<end_is_relative>
false</end_is_relative>
<is_3d>
false</is_3d>
<intensity>
63</intensity>
</GFXVector>
<GFXVector>
<startVertex>
<x>
3.0</x>
<y>
0.0</y>
<z>
0.0</z>
<w>
1.0</w>
<use_x>
true</use_x>
<use_y>
true</use_y>
<use_z>
true</use_z>
<use_w>
true</use_w>
<id>
4018710</id>
</startVertex>
<endVertex>
<x>
5.0</x>
<y>
1.0</y>
<z>
0.0</z>
<w>
1.0</w>
<use_x>
true</use_x>
<use_y>
true</use_y>
<use_z>
true</use_z>
<use_w>
true</use_w>
<id>
4018711</id>
</endVertex>
<pattern>
255</pattern>
<r>
255</r>
<g>
255</g>
<b>
255</b>
<a>
128</a>
<id>
286711</id>
<order>
22</order>
<start_neighbour_id>
-1</start_neighbour_id>
<end_neighbour_id>
-1</end_neighbour_id>
<start_is_relative>
false</start_is_relative>
<end_is_relative>
false</end_is_relative>
<is_3d>
false</is_3d>
<intensity>
63</intensity>
</GFXVector>
<GFXVector>
<startVertex>
<x>
5.0</x>
<y>
1.0</y>
<z>
0.0</z>
<w>
1.0</w>
<use_x>
true</use_x>
<use_y>
true</use_y>
<use_z>
true</use_z>
<use_w>
true</use_w>
<id>
4018712</id>
</startVertex>
<endVertex>
<x>
6.0</x>
<y>
0.0</y>
<z>
0.0</z>
<w>
1.0</w>
<use_x>
true</use_x>
<use_y>
true</use_y>
<use_z>
true</use_z>
<use_w>
true</use_w>
<id>
4018713</id>
</endVertex>
<pattern>
255</pattern>
<r>
255</r>
<g>
255</g>
<b>
255</b>
<a>
128</a>
<id>
286712</id>
<order>
23</order>
<start_neighbour_id>
-1</start_neighbour_id>
<end_neighbour_id>
-1</end_neighbour_id>
<start_is_relative>
false</start_is_relative>
<end_is_relative>
false</end_is_relative>
<is_3d>
false</is_3d>
<intensity>
63</intensity>
</GFXVector>
<GFXVector>
<startVertex>
<x>
-2.0</x>
<y>
1.0</y>
<z>
0.0</z>
<w>
1.0</w>
<use_x>
true</use_x>
<use_y>
true</use_y>
<use_z>
true</use_z>
<use_w>
true</use_w>
<id>
4018714</id>
</startVertex>
<endVertex>
<x>
-4.0</x>
<y>
3.0</y>
<z>
0.0</z>
<w>
1.0</w>
<use_x>
true</use_x>
<use_y>
true</use_y>
<use_z>
true</use_z>
<use_w>
true</use_w>
<id>
4018715</id>
</endVertex>
<pattern>
255</pattern>
<r>
255</r>
<g>
255</g>
<b>
255</b>
<a>
128</a>
<id>
286713</id>
<order>
24</order>
<start_neighbour_id>
-1</start_neighbour_id>
<end_neighbour_id>
-1</end_neighbour_id>
<start_is_relative>
false</start_is_relative>
<end_is_relative>
false</end_is_relative>
<is_3d>
false</is_3d>
<intensity>
63</intensity>
</GFXVector>
<GFXVector>
<startVertex>
<x>
-4.0</x>
<y>
3.0</y>
<z>
0.0</z>
<w>
1.0</w>
<use_x>
true</use_x>
<use_y>
true</use_y>
<use_z>
true</use_z>
<use_w>
true</use_w>
<id>
4018716</id>
</startVertex>
<endVertex>
<x>
-6.0</x>
<y>
2.0</y>
<z>
0.0</z>
<w>
1.0</w>
<use_x>
true</use_x>
<use_y>
true</use_y>
<use_z>
true</use_z>
<use_w>
true</use_w>
<id>
4018717</id>
</endVertex>
<pattern>
255</pattern>
<r>
255</r>
<g>
255</g>
<b>
255</b>
<a>
128</a>
<id>
286714</id>
<order>
25</order>
<start_neighbour_id>
-1</start_neighbour_id>
<end_neighbour_id>
-1</end_neighbour_id>
<start_is_relative>
false</start_is_relative>
<end_is_relative>
false</end_is_relative>
<is_3d>
false</is_3d>
<intensity>
63</intensity>
</GFXVector>
<GFXVector>
<startVertex>
<x>
-3.0</x>
<y>
0.0</y>
<z>
0.0</z>
<w>
1.0</w>
<use_x>
true</use_x>
<use_y>
true</use_y>
<use_z>
true</use_z>
<use_w>
true</use_w>
<id>
4018718</id>
</startVertex>
<endVertex>
<x>
-5.0</x>
<y>
1.0</y>
<z>
0.0</z>
<w>
1.0</w>
<use_x>
true</use_x>
<use_y>
true</use_y>
<use_z>
true</use_z>
<use_w>
true</use_w>
<id>
4018719</id>
</endVertex>
<pattern>
255</pattern>
<r>
255</r>
<g>
255</g>
<b>
255</b>
<a>
128</a>
<id>
286715</id>
<order>
26</order>
<start_neighbour_id>
-1</start_neighbour_id>
<end_neighbour_id>
-1</end_neighbour_id>
<start_is_relative>
false</start_is_relative>
<end_is_relative>
false</end_is_relative>
<is_3d>
false</is_3d>
<intensity>
63</intensity>
</GFXVector>
<GFXVector>
<startVertex>
<x>
-5.0</x>
<y>
1.0</y>
<z>
0.0</z>
<w>
1.0</w>
<use_x>
true</use_x>
<use_y>
true</use_y>
<use_z>
true</use_z>
<use_w>
true</use_w>
<id>
4018720</id>
</startVertex>
<endVertex>
<x>
-6.0</x>
<y>
0.0</y>
<z>
0.0</z>
<w>
1.0</w>
<use_x>
true</use_x>
<use_y>
true</use_y>
<use_z>
true</use_z>
<use_w>
true</use_w>
<id>
4018721</id>
</endVertex>
<pattern>
255</pattern>
<r>
255</r>
<g>
255</g>
<b>
255</b>
<a>
128</a>
<id>
286716</id>
<order>
27</order>
<start_neighbour_id>
-1</start_neighbour_id>
<end_neighbour_id>
-1</end_neighbour_id>
<start_is_relative>
false</start_is_relative>
<end_is_relative>
false</end_is_relative>
<is_3d>
false</is_3d>
<intensity>
63</intensity>
</GFXVector>
</GFXVectorList>
